OpenDartReader/__init__.py
OpenDartReader/_utils.py
OpenDartReader/dart.py
OpenDartReader/dart_event.py
OpenDartReader/dart_finstate.py
OpenDartReader/dart_list.py
OpenDartReader/dart_regstate.py
OpenDartReader/dart_report.py
OpenDartReader/dart_search.py
OpenDartReader/dart_share.py
OpenDartReader/dart_utils.py
OpenDartReader/search.py
OpenDartReader/api/__init__.py
OpenDartReader/api/dart_report.py
OpenDartReader/api/dart_search.py
OpenDartReader/api/finstate.py
OpenDartReader/api/report.py
OpenDartReader/api/search.py
OpenDartReader/api/share.py
OpenDartReader-0.2.1.dist-info/METADATA
OpenDartReader-0.2.1.dist-info/WHEEL
OpenDartReader-0.2.1.dist-info/top_level.txt
OpenDartReader-0.2.1.dist-info/RECORD
